python_lib_2/__init__.py
python_lib_2/main.py
python_lib_2-1.0.0.dist-info/METADATA
python_lib_2-1.0.0.dist-info/WHEEL
python_lib_2-1.0.0.dist-info/entry_points.txt
python_lib_2-1.0.0.dist-info/top_level.txt
python_lib_2-1.0.0.dist-info/RECORD
